coordinax/__init__.py
coordinax/_version.py
coordinax/_version.pyi
coordinax/angle.py
coordinax/distance.py
coordinax/frames.py
coordinax/ops.py
coordinax/py.typed
coordinax/setup_package.py
coordinax/vecs.py
coordinax/_coordinax_space_frames/__init__.py
coordinax/_coordinax_space_frames/base.py
coordinax/_coordinax_space_frames/frame_transforms.py
coordinax/_coordinax_space_frames/galactocentric.py
coordinax/_coordinax_space_frames/icrs.py
coordinax/_coordinax_space_frames/_interop/__init__.py
coordinax/_coordinax_space_frames/_interop/optional_deps.py
coordinax/_coordinax_space_frames/_interop/interop_astropy/__init__.py
coordinax/_coordinax_space_frames/_interop/interop_astropy/frames.py
coordinax/_interop/__init__.py
coordinax/_interop/optional_deps.py
coordinax/_interop/coordinax_interop_astropy/__init__.py
coordinax/_interop/coordinax_interop_astropy/constructors.py
coordinax/_interop/coordinax_interop_astropy/converters.py
coordinax/_interop/coordinax_interop_astropy/distance.py
coordinax/_src/__init__.py
coordinax/_src/angles.py
coordinax/_src/custom_types.py
coordinax/_src/promotion_rule.py
coordinax/_src/utils.py
coordinax/_src/distances/__init__.py
coordinax/_src/distances/base.py
coordinax/_src/distances/custom_types.py
coordinax/_src/distances/funcs.py
coordinax/_src/distances/measures.py
coordinax/_src/distances/register_constructors.py
coordinax/_src/distances/register_converters.py
coordinax/_src/distances/register_primitives.py
coordinax/_src/distances/register_unxt.py
coordinax/_src/frames/__init__.py
coordinax/_src/frames/api.py
coordinax/_src/frames/base.py
coordinax/_src/frames/coordinate.py
coordinax/_src/frames/errors.py
coordinax/_src/frames/example.py
coordinax/_src/frames/null.py
coordinax/_src/frames/register_frames.py
coordinax/_src/frames/register_ops.py
coordinax/_src/frames/register_primitives.py
coordinax/_src/frames/register_vectorapi.py
coordinax/_src/frames/xfm.py
coordinax/_src/operators/__init__.py
coordinax-0.23.2.dist-info/METADATA
coordinax-0.23.2.dist-info/WHEEL
coordinax-0.23.2.dist-info/licenses/LICENSE
coordinax-0.23.2.dist-info/RECORD
