Metadata-Version: 2.4
Name: coordinax
Version: 0.23.2
Summary: Coordinates in JAX
Project-URL: Bug Tracker, https://github.com/GalacticDynamics/coordinax/issues
Project-URL: Changelog, https://github.com/GalacticDynamics/coordinax/releases
Project-URL: Discussions, https://github.com/GalacticDynamics/coordinax/discussions
Project-URL: Homepage, https://github.com/GalacticDynamics/coordinax
Author-email: Coordinax Devs <nstarman@users.noreply.github.com>, Nathaniel Starkman <nstarman@users.noreply.github.com>, Adrian Price-Whelan <adrn@users.noreply.github.com>
License-Expression: MIT
License-File: LICENSE
Classifier: Development Status :: 3 - Alpha
Classifier: Intended Audience :: Developers
Classifier: Intended Audience :: Science/Research
Classifier: Operating System :: OS Independent
Classifier: Programming Language :: Python
Classifier: Programming Language :: Python :: 3
Classifier: Programming Language :: Python :: 3 :: Only
Classifier: Programming Language :: Python :: 3.11
Classifier: Programming Language :: Python :: 3.12
Classifier: Programming Language :: Python :: 3.13
Classifier: Topic :: Scientific/Engineering
Classifier: Typing :: Typed
Requires-Python: >=3.11
Requires-Dist: astropy>=7.0.0
Requires-Dist: beartype>=0.21.0
Requires-Dist: dataclassish>=0.8.0
Requires-Dist: equinox>=0.13.2
Requires-Dist: jax>=0.6.0
Requires-Dist: jaxlib>=0.6.0
Requires-Dist: jaxtyping>=0.3.3
Requires-Dist: optional-dependencies>=0.3.2
Requires-Dist: plum-dispatch>=2.5.7
Requires-Dist: quax-blocks>=0.4.0
Requires-Dist: quax>=0.2.1
Requires-Dist: quaxed>=0.10.4
Requires-Dist: typing-extensions>=4.13.2
Requires-Dist: unxt>=1.10.3
Requires-Dist: wadler-lindig>=0.1.6
Requires-Dist: xmmutablemap>=0.1
